star_ray/__init__.py
star_ray/agent/__init__.py
star_ray/agent/_wrapper_agent.py
star_ray/agent/_wrapper_observations.py
star_ray/agent/agent.py
star_ray/agent/agent_routed.py
star_ray/agent/component/__init__.py
star_ray/agent/component/actuator.py
star_ray/agent/component/attempt.py
star_ray/agent/component/component.py
star_ray/agent/component/on_awake.py
star_ray/agent/component/sensor.py
star_ray/agent/component/sensor_io.py
star_ray/environment/__init__.py
star_ray/environment/ambient.py
star_ray/environment/environment.py
star_ray/event/__init__.py
star_ray/event/action_event.py
star_ray/event/event.py
star_ray/event/event_kill.py
star_ray/event/observation_event.py
star_ray/event/user_event/__init__.py
star_ray/event/user_event/joystickevent.py
star_ray/event/user_event/keyevent.py
star_ray/event/user_event/mouseevent.py
star_ray/event/user_event/visibilityevent.py
star_ray/event/user_event/windowevent.py
star_ray/pubsub/__init__.py
star_ray/pubsub/_action.py
star_ray/pubsub/_pubsub.py
star_ray/pubsub/_topic_publisher.py
star_ray/pubsub/_type_publisher.py
star_ray/ui/__init__.py
star_ray/ui/window_configuration.py
star_ray/utils/__init__.py
star_ray/utils/_async.py
star_ray/utils/_cls_utils.py
star_ray/utils/_dict_observer.py
star_ray/utils/_logging.py
star_ray/utils/_templating.py
star_ray/utils/_types.py
star_ray/utils/_uuid.py
star_ray/utils/dict_utils.py
star_ray/utils/error.py
star_ray/utils/literal_eval.py
star_ray/utils/type_routing.py
star_ray-0.0.8.dist-info/LICENSE
star_ray-0.0.8.dist-info/METADATA
star_ray-0.0.8.dist-info/WHEEL
star_ray-0.0.8.dist-info/top_level.txt
star_ray-0.0.8.dist-info/RECORD
