Metadata-Version: 2.1
Name: star_ray
Version: 0.0.8
Summary: A multi-agent simulation platform based on the distributed computing platform `ray`.
Author-email: Benedict Wilkins <benrjw@gmail.com>
License: GNU GENERAL PUBLIC LICENSE
Project-URL: Repository, https://github.com/dicelab-rhul/star-ray
Requires-Python: >=3.10
License-File: LICENSE
Requires-Dist: ray>=2.9.1
Requires-Dist: starlette<=0.34.0
Requires-Dist: jinja2
Requires-Dist: pydantic
Requires-Dist: deepmerge
Requires-Dist: cerberus
Provides-Extra: pygame
Requires-Dist: star-ray-pygame>=0.0.8; extra == "pygame"
Provides-Extra: xml
Requires-Dist: star-ray-xml>=0.0.6; extra == "xml"
